Tirrilee_Contact_Form/__init__.py
Tirrilee_Contact_Form/forms.py
Tirrilee_Contact_Form/settings.py
Tirrilee_Contact_Form/signals.py
Tirrilee_Contact_Form/spam_filters.py
Tirrilee_Contact_Form/urls.py
Tirrilee_Contact_Form/views.py
Tirrilee_Contact_Form/widgets.py
Tirrilee_Contact_Form/templates/tirrilee_contact_form/contact_form.html
Tirrilee_Contact_Form/templates/tirrilee_contact_form/email_body.html
Tirrilee_Contact_Form/templates/tirrilee_contact_form/email_body.txt
Tirrilee_Contact_Form/templatetags/__init__.py
Tirrilee_Contact_Form/templatetags/tirrilee_contact_tags.py
Tirrilee_Contact_Form-0.3.1.dist-info/METADATA
Tirrilee_Contact_Form-0.3.1.dist-info/RECORD
Tirrilee_Contact_Form-0.3.1.dist-info/WHEEL
Tirrilee_Contact_Form-0.3.1.dist-info/top_level.txt
