Metadata-Version: 2.1
Name: Tirrilee-Contact-Form
Version: 0.3.1
Summary: Contact Form Package From Tirrilee
Home-page: https://github.com/Tirrilee/Django-Packages/Contact-Form/
Author: Aiden
Author-email: aiden@tirrilee.io
License: MIT
Platform: UNKNOWN
Requires-Dist: Django (>=2.0)
